MANIFEST.in
README.md
setup.cfg
setup.py
nbg/__init__.py
nbg/nbg.py
nbg_py.egg-info/PKG-INFO
nbg_py.egg-info/SOURCES.txt
nbg_py.egg-info/dependency_links.txt
nbg_py.egg-info/top_level.txt