Metadata-Version: 1.0
Name: nbg-py
Version: 0.1
Summary: Client for National Bank of Georgia currency api
Home-page: https://github.com/ent1c3d/NBG-py
Author: Goga Patarkatsishvili
Author-email: ent1c3d@gmail.com
License: MIT
Platform: UNKNOWN
